README.txt
bootstrap.py
buildout.cfg
setup.py
docs/HISTORY.txt
src/five/__init__.py
src/five.megrok.layout.egg-info/PKG-INFO
src/five.megrok.layout.egg-info/SOURCES.txt
src/five.megrok.layout.egg-info/dependency_links.txt
src/five.megrok.layout.egg-info/namespace_packages.txt
src/five.megrok.layout.egg-info/not-zip-safe
src/five.megrok.layout.egg-info/requires.txt
src/five.megrok.layout.egg-info/top_level.txt
src/five/megrok/__init__.py
src/five/megrok/layout/__init__.py
src/five/megrok/layout/components.py
src/five/megrok/layout/configure.zcml
src/five/megrok/layout/ftesting.zcml
src/five/megrok/layout/meta.py
src/five/megrok/layout/meta.zcml
src/five/megrok/layout/testing.py
src/five/megrok/layout/ftests/__init__.py
src/five/megrok/layout/ftests/test_grok_functional.py
src/five/megrok/layout/ftests/layout/__init__.py
src/five/megrok/layout/ftests/layout/layout.py
src/five/megrok/layout/ftests/layout/page.py
src/five/megrok/layout/ftests/layout/pagesecurity.py
src/five/megrok/layout/ftests/layout/resources.py
src/five/megrok/layout/ftests/layout/page_templates/master.pt
src/five/megrok/layout/ftests/layout/page_templates/mybigview.pt
src/five/megrok/layout/ftests/layout/pagesecurity_templates/master.pt
src/five/megrok/layout/ftests/layout/static/empty.js