Metadata-Version: 1.0
Name: five.megrok.layout
Version: 1.2
Summary: A grok layout component package for Zope 2
Home-page: http://svn.zope.org/five.megrok.layout/
Author: Sylvain Viollon and Vincent Fretin
Author-email: grok-dev@zope.org
License: ZPL
Keywords: layout grok zope2
Platform: UNKNOWN
Classifier: Environment :: Web Environment
Classifier: Intended Audience :: Developers
Classifier: License :: OSI Approved :: Zope Public License
Classifier: Programming Language :: Python
Classifier: Topic :: Software Development :: Libraries :: Python Modules
Classifier: Framework :: Zope2
